django_auto_permissions/__init__.py
django_auto_permissions/apps.py
django_auto_permissions/permission_generation.py
django_auto_permissions/permissions.py
django_auto_permissions/registration.py
django_auto_permissions/viewset_analysis.py
django_auto_permissions/tests/__init__.py
django_auto_permissions/tests/test_viewset_analysis.py
django_auto_permissions-0.1.20.dist-info/LICENSE
django_auto_permissions-0.1.20.dist-info/METADATA
django_auto_permissions-0.1.20.dist-info/WHEEL
django_auto_permissions-0.1.20.dist-info/top_level.txt
django_auto_permissions-0.1.20.dist-info/RECORD
