Metadata-Version: 2.1
Name: django-auto-permissions
Version: 0.1.20
Summary: Automated permission generation for Django viewsets
Home-page: https://github.com/jeetkreditserve/django_auto_permissions
Author: Jeet Padhya
Author-email: jeet.padhya@hotmail.com
License: UNKNOWN
Platform: UNKNOWN
Classifier: Framework :: Django
Classifier: Intended Audience :: Developers
Classifier: Programming Language :: Python :: 3
Classifier: License :: OSI Approved :: MIT License
License-File: LICENSE
Requires-Dist: Django (>=3.2)
